pevx/__init__.py
pevx/__main__.py
pevx/cli.py
pevx/commands/__init__.py
pevx/commands/aws_each.py
pevx/commands/docker.py
pevx/commands/pyclient.py
pevx/commands/uv.py
pevx/core/__init__.py
pevx/core/engine.py
pevx/utils/__init__.py
pevx/utils/codeartifact.py
pevx/utils/config.py
pevx-1.6.0.dist-info/METADATA
pevx-1.6.0.dist-info/WHEEL
pevx-1.6.0.dist-info/entry_points.txt
pevx-1.6.0.dist-info/RECORD
