Metadata-Version: 2.4
Name: pevx
Version: 1.6.0
Summary: Prudentia CLI - Development tools for Prudentia internal developers
Author-email: Adrianh Dao <doadrianh@gmail.com>
License: Proprietary
Classifier: Intended Audience :: Developers
Classifier: Programming Language :: Python :: 3
Classifier: Programming Language :: Python :: 3.12
Requires-Python: >=3.12
Requires-Dist: awscli>=1.40.18
Requires-Dist: click>=8.1.3
Requires-Dist: openapi-python-client<0.25.0,>=0.24.3
Requires-Dist: tomlkit>=0.13.3
